{
  "ts": "2026-02-08T21:58:23+00:00",
  "pools": [
    {
      "chain": "Base",
      "pair": "ETH/USDC",
      "volatility_24h_pct": 4.85,
      "volume_24h_usd": 1739342.48,
      "fee_apr_est_pct": 3.22
    },
    {
      "chain": "Arbitrum",
      "pair": "ETH/USDT",
      "volatility_24h_pct": 1.63,
      "volume_24h_usd": 1168524.66,
      "fee_apr_est_pct": 7.2
    },
    {
      "chain": "OP",
      "pair": "WBTC/ETH",
      "volatility_24h_pct": 4.64,
      "volume_24h_usd": 1772192.6,
      "fee_apr_est_pct": 10.65
    }
  ]
}