{
  "ts": "2025-10-04T05:50:43+00:00",
  "pools": [
    {
      "chain": "Base",
      "pair": "ETH/USDC",
      "volatility_24h_pct": 1.52,
      "volume_24h_usd": 1168675.13,
      "fee_apr_est_pct": 3.47
    },
    {
      "chain": "Arbitrum",
      "pair": "ETH/USDT",
      "volatility_24h_pct": 1.61,
      "volume_24h_usd": 400175.36,
      "fee_apr_est_pct": 12.48
    },
    {
      "chain": "OP",
      "pair": "WBTC/ETH",
      "volatility_24h_pct": 4.13,
      "volume_24h_usd": 1990828.23,
      "fee_apr_est_pct": 8.77
    }
  ]
}