{
  "ts": "2025-10-06T20:50:52+00:00",
  "pools": [
    {
      "chain": "Base",
      "pair": "ETH/USDC",
      "volatility_24h_pct": 1.25,
      "volume_24h_usd": 1275948.15,
      "fee_apr_est_pct": 16.17
    },
    {
      "chain": "Arbitrum",
      "pair": "ETH/USDT",
      "volatility_24h_pct": 1.98,
      "volume_24h_usd": 346820.9,
      "fee_apr_est_pct": 5.42
    },
    {
      "chain": "OP",
      "pair": "WBTC/ETH",
      "volatility_24h_pct": 3.18,
      "volume_24h_usd": 433965.59,
      "fee_apr_est_pct": 5.76
    }
  ]
}