{
  "ts": "2025-10-06T22:24:49+00:00",
  "pools": [
    {
      "chain": "Base",
      "pair": "ETH/USDC",
      "volatility_24h_pct": 3.72,
      "volume_24h_usd": 243284.17,
      "fee_apr_est_pct": 8.69
    },
    {
      "chain": "Arbitrum",
      "pair": "ETH/USDT",
      "volatility_24h_pct": 1.91,
      "volume_24h_usd": 1981521.78,
      "fee_apr_est_pct": 12.73
    },
    {
      "chain": "OP",
      "pair": "WBTC/ETH",
      "volatility_24h_pct": 2.16,
      "volume_24h_usd": 1260599.27,
      "fee_apr_est_pct": 14.97
    }
  ]
}