{
  "ts": "2026-02-13T19:29:57+00:00",
  "pools": [
    {
      "chain": "Base",
      "pair": "ETH/USDC",
      "volatility_24h_pct": 3.89,
      "volume_24h_usd": 374989.33,
      "fee_apr_est_pct": 11.9
    },
    {
      "chain": "Arbitrum",
      "pair": "ETH/USDT",
      "volatility_24h_pct": 2.31,
      "volume_24h_usd": 1206516.77,
      "fee_apr_est_pct": 16.74
    },
    {
      "chain": "OP",
      "pair": "WBTC/ETH",
      "volatility_24h_pct": 1.1,
      "volume_24h_usd": 669872.14,
      "fee_apr_est_pct": 13.66
    }
  ]
}