{
  "ts": "2025-10-09T01:57:24+00:00",
  "pools": [
    {
      "chain": "Base",
      "pair": "ETH/USDC",
      "volatility_24h_pct": 1.03,
      "volume_24h_usd": 190374.75,
      "fee_apr_est_pct": 16.19
    },
    {
      "chain": "Arbitrum",
      "pair": "ETH/USDT",
      "volatility_24h_pct": 2.87,
      "volume_24h_usd": 1390197.77,
      "fee_apr_est_pct": 11.71
    },
    {
      "chain": "OP",
      "pair": "WBTC/ETH",
      "volatility_24h_pct": 3.63,
      "volume_24h_usd": 1055362.45,
      "fee_apr_est_pct": 9.54
    }
  ]
}