{
  "ts": "2026-02-14T16:42:09+00:00",
  "pools": [
    {
      "chain": "Base",
      "pair": "ETH/USDC",
      "volatility_24h_pct": 4.09,
      "volume_24h_usd": 1146267.6,
      "fee_apr_est_pct": 17.66
    },
    {
      "chain": "Arbitrum",
      "pair": "ETH/USDT",
      "volatility_24h_pct": 4.53,
      "volume_24h_usd": 493235.84,
      "fee_apr_est_pct": 10.21
    },
    {
      "chain": "OP",
      "pair": "WBTC/ETH",
      "volatility_24h_pct": 3.36,
      "volume_24h_usd": 1988648.52,
      "fee_apr_est_pct": 12.01
    }
  ]
}