{
  "ts": "2026-07-14T04:11:04+00:00",
  "pools": [
    {
      "chain": "Base",
      "pair": "ETH/USDC",
      "volatility_24h_pct": 0.95,
      "volume_24h_usd": 1316470.59,
      "fee_apr_est_pct": 2.47
    },
    {
      "chain": "Arbitrum",
      "pair": "ETH/USDT",
      "volatility_24h_pct": 2.3,
      "volume_24h_usd": 300185.1,
      "fee_apr_est_pct": 14.92
    },
    {
      "chain": "OP",
      "pair": "WBTC/ETH",
      "volatility_24h_pct": 1.8,
      "volume_24h_usd": 1222405.99,
      "fee_apr_est_pct": 8.43
    }
  ]
}