{
  "ts": "2026-07-19T06:15:19+00:00",
  "pools": [
    {
      "chain": "Base",
      "pair": "ETH/USDC",
      "volatility_24h_pct": 1.35,
      "volume_24h_usd": 1243893.32,
      "fee_apr_est_pct": 4.6
    },
    {
      "chain": "Arbitrum",
      "pair": "ETH/USDT",
      "volatility_24h_pct": 4.56,
      "volume_24h_usd": 1151816.19,
      "fee_apr_est_pct": 15.66
    },
    {
      "chain": "OP",
      "pair": "WBTC/ETH",
      "volatility_24h_pct": 2.98,
      "volume_24h_usd": 651491.77,
      "fee_apr_est_pct": 12.43
    }
  ]
}