{
  "ts": "2026-01-23T18:48:35+00:00",
  "pools": [
    {
      "chain": "Base",
      "pair": "ETH/USDC",
      "volatility_24h_pct": 3.84,
      "volume_24h_usd": 1484264.34,
      "fee_apr_est_pct": 17.63
    },
    {
      "chain": "Arbitrum",
      "pair": "ETH/USDT",
      "volatility_24h_pct": 3.06,
      "volume_24h_usd": 1490931.1,
      "fee_apr_est_pct": 9.01
    },
    {
      "chain": "OP",
      "pair": "WBTC/ETH",
      "volatility_24h_pct": 1.35,
      "volume_24h_usd": 927888.75,
      "fee_apr_est_pct": 16.51
    }
  ]
}