{
  "ts": "2025-12-15T21:28:33+00:00",
  "pools": [
    {
      "chain": "Base",
      "pair": "ETH/USDC",
      "volatility_24h_pct": 0.57,
      "volume_24h_usd": 1075096.34,
      "fee_apr_est_pct": 15.96
    },
    {
      "chain": "Arbitrum",
      "pair": "ETH/USDT",
      "volatility_24h_pct": 1.72,
      "volume_24h_usd": 1081501.73,
      "fee_apr_est_pct": 6.66
    },
    {
      "chain": "OP",
      "pair": "WBTC/ETH",
      "volatility_24h_pct": 3.08,
      "volume_24h_usd": 1414314.76,
      "fee_apr_est_pct": 16.64
    }
  ]
}