{
  "ts": "2025-12-06T12:53:34+00:00",
  "pools": [
    {
      "chain": "Base",
      "pair": "ETH/USDC",
      "volatility_24h_pct": 3.42,
      "volume_24h_usd": 1891793.59,
      "fee_apr_est_pct": 12.03
    },
    {
      "chain": "Arbitrum",
      "pair": "ETH/USDT",
      "volatility_24h_pct": 4.95,
      "volume_24h_usd": 1127049.28,
      "fee_apr_est_pct": 6.57
    },
    {
      "chain": "OP",
      "pair": "WBTC/ETH",
      "volatility_24h_pct": 3.81,
      "volume_24h_usd": 1076786.08,
      "fee_apr_est_pct": 7.63
    }
  ]
}