{
  "ts": "2025-11-07T17:50:47+00:00",
  "pools": [
    {
      "chain": "Base",
      "pair": "ETH/USDC",
      "volatility_24h_pct": 3.76,
      "volume_24h_usd": 648296.78,
      "fee_apr_est_pct": 17.75
    },
    {
      "chain": "Arbitrum",
      "pair": "ETH/USDT",
      "volatility_24h_pct": 4.2,
      "volume_24h_usd": 922585.16,
      "fee_apr_est_pct": 15.92
    },
    {
      "chain": "OP",
      "pair": "WBTC/ETH",
      "volatility_24h_pct": 2.85,
      "volume_24h_usd": 1136473.23,
      "fee_apr_est_pct": 6.19
    }
  ]
}